numpy_2425/__init__.py
numpy_2425/operations.py
numpy_2425-0.1.dist-info/METADATA
numpy_2425-0.1.dist-info/WHEEL
numpy_2425-0.1.dist-info/top_level.txt
numpy_2425-0.1.dist-info/RECORD
