Metadata-Version: 2.1
Name: numpy-2425
Version: 0.1
Summary: A custom NLP package
Author: Your Name
